mgzip/__init__.py
mgzip/__main__.py
mgzip/multiProcGzip.py
mgzip2-0.2.6.dist-info/LICENSE
mgzip2-0.2.6.dist-info/METADATA
mgzip2-0.2.6.dist-info/WHEEL
mgzip2-0.2.6.dist-info/top_level.txt
mgzip2-0.2.6.dist-info/RECORD
